luaparser/__init__.py
luaparser/__main__.py
luaparser/ast.py
luaparser/astnodes.py
luaparser/builder.py
luaparser/printers.py
luaparser/parser/LuaLexer.py
luaparser/parser/LuaLexerBase.py
luaparser/parser/LuaParser.py
luaparser/parser/LuaParserListener.py
luaparser/parser/LuaParserVisitor.py
luaparser/parser/__init__.py
luaparser/parser/transformGrammar.py
luaparser/tests/__init__.py
luaparser/tests/test_ast.py
luaparser/tests/test_comments.py
luaparser/tests/test_expressions.py
luaparser/tests/test_integration.py
luaparser/tests/test_lineno.py
luaparser/tests/test_lua_output.py
luaparser/tests/test_statements.py
luaparser/tests/test_types_values.py
luaparser/tests/test_variables.py
luaparser/utils/__init__.py
luaparser/utils/tests.py
luaparser/utils/visitor.py
luaparser-3.3.1.dist-info/licenses/LICENSE.txt
luaparser-3.3.1.dist-info/METADATA
luaparser-3.3.1.dist-info/WHEEL
luaparser-3.3.1.dist-info/entry_points.txt
luaparser-3.3.1.dist-info/top_level.txt
luaparser-3.3.1.dist-info/RECORD
