Metadata-Version: 2.4
Name: luaparser
Version: 3.3.1
Summary: A lua parser in Python
Home-page: https://github.com/boolangery/py-lua-parser
Download-URL: https://github.com/boolangery/py-lua-parser/archive/3.3.1.tar.gz
Author: Eliott Dumeix
Author-email: eliott.dumeix@gmail.com
License: MIT
Classifier: Intended Audience :: Developers
Classifier: Topic :: Software Development :: Libraries :: Python Modules
Classifier: Operating System :: OS Independent
Classifier: Programming Language :: Python :: 3.6
Classifier: Programming Language :: Python :: 3.7
Classifier: Programming Language :: Python :: 3.8
Classifier: Programming Language :: Python :: 3.9
License-File: LICENSE.txt
Requires-Dist: antlr4-python3-runtime==4.13.2
Requires-Dist: multimethod
Dynamic: author
Dynamic: author-email
Dynamic: classifier
Dynamic: description
Dynamic: download-url
Dynamic: home-page
Dynamic: license
Dynamic: license-file
Dynamic: requires-dist
Dynamic: summary
